cslug/__init__.py
cslug/_cc.py
cslug/_cslug.py
cslug/_headers.py
cslug/_pointers.py
cslug/_stdlib.py
cslug/_struct.py
cslug/_types_file.py
cslug/building.py
cslug/c_parse.py
cslug/exceptions.py
cslug/misc.py
cslug/stdlib.json
cslug/stdlib.py
cslug-1.0.0.dist-info/LICENSE
cslug-1.0.0.dist-info/METADATA
cslug-1.0.0.dist-info/WHEEL
cslug-1.0.0.dist-info/top_level.txt
cslug-1.0.0.dist-info/RECORD
