Metadata-Version: 2.1
Name: cslug
Version: 1.0.0
Summary: Quick and painless wrapping C code into Python
Author-email: Brénainn Woodsend <bwoodsend@gmail.com>
License: MIT License
Project-URL: Homepage, https://github.com/bwoodsend/cslug
Classifier: License :: OSI Approved :: MIT License
Classifier: Programming Language :: Python :: 3
Classifier: Programming Language :: Python :: 3.8
Classifier: Programming Language :: Python :: 3.9
Classifier: Programming Language :: Python :: 3.10
Classifier: Programming Language :: Python :: 3.11
Classifier: Programming Language :: Python :: 3.12
Classifier: Programming Language :: Python :: 3.13
Requires-Python: >=3.8
License-File: LICENSE
